amarillo/plugins/__init__.py
amarillo/plugins/metrics/__init__.py
amarillo/plugins/metrics/metrics.py
amarillo/plugins/metrics/secrets.py
amarillo_metrics-2.0.0.dist-info/LICENSE
amarillo_metrics-2.0.0.dist-info/METADATA
amarillo_metrics-2.0.0.dist-info/WHEEL
amarillo_metrics-2.0.0.dist-info/top_level.txt
amarillo_metrics-2.0.0.dist-info/RECORD
