Metadata-Version: 2.1
Name: amarillo-metrics
Version: 2.0.0
Summary: Prometheus metrics for Amarillo
License: GNU AFFERO GENERAL PUBLIC LICENSE
License-File: LICENSE
Requires-Dist: fastapi
Requires-Dist: amarillo
Requires-Dist: prometheus-fastapi-instrumentator
Requires-Dist: prometheus-client
